aiogrpcclient/__init__.py
aiogrpcclient/base.py
aiogrpcclient-1.3.20.dist-info/METADATA
aiogrpcclient-1.3.20.dist-info/WHEEL
aiogrpcclient-1.3.20.dist-info/RECORD
