Metadata-Version: 2.1
Name: aiogrpcclient
Version: 1.3.20
Summary: 
Author: Pasha Podolsky
Author-email: ppodolsky@me.com
Requires-Python: >=3.8,<4.0
Classifier: Programming Language :: Python :: 3
Classifier: Programming Language :: Python :: 3.8
Classifier: Programming Language :: Python :: 3.9
Classifier: Programming Language :: Python :: 3.10
Classifier: Programming Language :: Python :: 3.11
Classifier: Programming Language :: Python :: 3.12
Requires-Dist: aiokit (>=1.3.9,<2.0.0)
Requires-Dist: grpcio (>=1.70.0,<2.0.0)
Requires-Dist: izihawa-utils (>=1.2.3,<2.0.0)
Requires-Dist: pyyaml (>=6.0.2,<7.0.0)
Requires-Dist: tenacity (>=9.0.0,<9.1.0)
Requires-Dist: termcolor (>=2.5.0,<3.0.0)
